agent/__init__.py
agent/__main__.py
agent/constants.py
agent/logger.py
agent/certificates/__init__.py
agent/certificates/certificate_client.py
agent/certificates/certificate_config_generator.py
agent/commands/__init__.py
agent/commands/dispatcher.py
agent/commands/docker_commands.py
agent/commands/metrics.py
agent/commands/service.py
agent/commands/service_config_decryptor.py
agent/commands/service_config_provider.py
agent/commands/service_creator.py
agent/commands/service_delete.py
agent/commands/service_provision.py
agent/commands/service_restart.py
agent/commands/service_status.py
agent/commands/shell_executor.py
agent/commands/uninstall.py
agent/commands/utils.py
agent/communication/__init__.py
agent/communication/message_processor.py
agent/config/__init__.py
agent/config/properties.py
agent/exceptions/__init__.py
agent/exceptions/agent_error.py
agent/rabbitmq/__init__.py
agent/rabbitmq/client.py
agent/rabbitmq/consumer.py
agent/rabbitmq/message_types.py
agent/rabbitmq/publisher.py
agent/rabbitmq/setup.py
agent/rabbitmq/rabbit_docker_compose/__init__.py
agent/rabbitmq/rabbit_docker_compose/docker-compose.yaml
agent/scheduler/__init__.py
agent/scheduler/metrics_task.py
agent/scheduler/scheduled_task.py
agent/scheduler/scheduled_tasks_manager.py
agent/scheduler/status_task.py
agent/services/__init__.py
agent/services/status_sender.py
agent/services/utils.py
agent/smart_card/__init__.py
agent/smart_card/smart_card_reader.py
agent/smart_card/smart_card_resolver.py
agent/websocket/__init__.py
agent/websocket/client.py
agent/websocket/utils.py
tests/__init__.py
tests/test_commands_dispatcher.py
tests/test_docker_commands.py
tests/test_message_processor.py
tests/test_metrics.py
tests/test_service_config_decryptor.py
tests/test_service_config_provider.py
tests/test_service_creator.py
tests/test_service_delete.py
tests/test_service_provision.py
tests/test_service_restart.py
tests/test_service_status.py
tests/test_shell_executor.py
tests/test_smart_card_reader.py
rexsio_agent-0.0.8.dist-info/LICENSE
rexsio_agent-0.0.8.dist-info/METADATA
rexsio_agent-0.0.8.dist-info/WHEEL
rexsio_agent-0.0.8.dist-info/entry_points.txt
rexsio_agent-0.0.8.dist-info/top_level.txt
rexsio_agent-0.0.8.dist-info/RECORD
