Metadata-Version: 2.1
Name: rexsio-agent
Version: 0.0.8
Summary: Rexsio Agent
Home-page: https://gitlab.com/rexsio/agent
Author: rexs.io sp. z o.o.
Author-email: hello@rexs.io
License: UNKNOWN
Platform: UNKNOWN
Classifier: Programming Language :: Python :: 3
Classifier: License :: OSI Approved :: MIT License
Requires-Dist: autobahn (==20.2.1)
Requires-Dist: Twisted (==19.10.0)
Requires-Dist: requests (==2.22.0)
Requires-Dist: psutil (==5.6.7)
Requires-Dist: docker (==4.2.0)
Requires-Dist: pyOpenSSL (==19.1.0)
Requires-Dist: service-identity (==18.1.0)
Requires-Dist: python-dotenv (==0.12.0)
Requires-Dist: pika (==1.1.0)
Requires-Dist: importlib-resources (==3.0.0)
Requires-Dist: pycryptodome (==3.9.8)
